flywheel_transfer_utils/FlywheelUtils.py
flywheel_transfer_utils/__init__.py
flywheel_transfer_utils/robust_api.py
flywheel_transfer_utils-0.2.4.dist-info/LICENSE
flywheel_transfer_utils-0.2.4.dist-info/METADATA
flywheel_transfer_utils-0.2.4.dist-info/WHEEL
flywheel_transfer_utils-0.2.4.dist-info/RECORD
