Metadata-Version: 2.1
Name: flywheel-transfer-utils
Version: 0.2.4
Summary: Common utilities for flywheel operations
Author: David Parker
Author-email: davidparker@flywheel.io
Requires-Python: >=3.12,<4.0
Classifier: Programming Language :: Python :: 3
Classifier: Programming Language :: Python :: 3.12
Requires-Dist: flywheel-sdk (>=19.3.0,<20.0.0)
Requires-Dist: fw-client (>=0.8.6,<0.9.0)
